CHANGES.txt
MANIFEST.in
README.md
setup.py
GeobricksGeostatistics.egg-info/PKG-INFO
GeobricksGeostatistics.egg-info/SOURCES.txt
GeobricksGeostatistics.egg-info/dependency_links.txt
GeobricksGeostatistics.egg-info/requires.txt
GeobricksGeostatistics.egg-info/top_level.txt
geobricks_geostatistics/__init__.py
geobricks_geostatistics/__init__.pyc
geobricks_geostatistics/config/__init__.py
geobricks_geostatistics/config/__init__.pyc
geobricks_geostatistics/config/config.py
geobricks_geostatistics/config/config.pyc
geobricks_geostatistics/core/__init__.py
geobricks_geostatistics/core/__init__.pyc
geobricks_geostatistics/core/raster.py
geobricks_geostatistics/core/raster.pyc
geobricks_geostatistics/rest/__init__.py
geobricks_geostatistics/rest/__init__.pyc
geobricks_geostatistics/rest/geostatistics_main.py
geobricks_geostatistics/rest/geostatistics_main.pyc
geobricks_geostatistics/rest/geostatistics_rest.py
geobricks_geostatistics/rest/geostatistics_rest.pyc
geobricks_geostatistics_test/__init__.py
geobricks_geostatistics_test/test_suite/__init__.py
geobricks_geostatistics_test/test_suite/pyproj_test.py
geobricks_geostatistics_test/test_suite/raster_test.py