Metadata-Version: 1.0
Name: GeobricksGeostatistics
Version: 0.0.4
Summary: Geobricks geostatistics library.
Home-page: http://pypi.python.org/pypi/GeobricksGISRaster/
Author: Simone Murzilli; Guido Barbaglia
Author-email: geobrickspy@gmail.com
License: LICENSE.txt
Keywords: geobricks,geoserver,gis,raster
Platform: UNKNOWN
